ssaw/__about__.py
ssaw/__init__.py
ssaw/assignments.py
ssaw/base.py
ssaw/exceptions.py
ssaw/export.py
ssaw/headquarters.py
ssaw/headquarters_schema.py
ssaw/interviews.py
ssaw/maps.py
ssaw/models.py
ssaw/questionnaires.py
ssaw/settings.py
ssaw/statistics.py
ssaw/users.py
ssaw/utils.py
ssaw/workspaces.py
ssaw-0.8.dist-info/licenses/LICENSE.txt
ssaw-0.8.dist-info/METADATA
ssaw-0.8.dist-info/WHEEL
ssaw-0.8.dist-info/top_level.txt
ssaw-0.8.dist-info/RECORD
