Metadata-Version: 2.4
Name: ssaw
Version: 0.8
Summary: Survey Solutions API Wrapper
Author-email: Zurab Sajaia <zsajaia@hotmail.com>
License: Copyright (c) Zurab Sajaia.
Project-URL: Homepage, https://github.com/vavalomi/ssaw
Project-URL: Bug Tracker, https://github.com/vavalomi/ssaw/issues
Keywords: Survey Solutions
Classifier: Development Status :: 4 - Beta
Classifier: Environment :: Console
Classifier: Environment :: Web Environment
Classifier: License :: OSI Approved :: MIT License
Classifier: Operating System :: OS Independent
Classifier: Programming Language :: Python
Classifier: Programming Language :: Python :: 3 :: Only
Classifier: Programming Language :: Python :: Implementation :: PyPy
Requires-Python: >=3.10
License-File: LICENSE.txt
Requires-Dist: pydantic
Requires-Dist: requests
Requires-Dist: sgqlc
Provides-Extra: test
Requires-Dist: flake8; extra == "test"
Requires-Dist: flake8-import-order; extra == "test"
Requires-Dist: pytest; extra == "test"
Requires-Dist: pytest-cov; extra == "test"
Requires-Dist: pytest-order; extra == "test"
Requires-Dist: python-dotenv; extra == "test"
Requires-Dist: sphinx; extra == "test"
Requires-Dist: vcrpy; extra == "test"
Dynamic: license-file
